caujax/__init__.py
caujax-0.1.1.dist-info/LICENSE
caujax-0.1.1.dist-info/WHEEL
caujax-0.1.1.dist-info/METADATA
caujax-0.1.1.dist-info/RECORD
